data_memory_4bit.v
// =====================================================================
// Data Memory: 16 locations x 4 bits, byte... (nibble) addressable.
// Synchronous write, asynchronous (combinational) read.
// =====================================================================
module data_memory_4bit (
    input  wire        clk,
    input  wire        we,
    input  wire [3:0]  addr,
    input  wire [3:0]  write_data,
    output wire [3:0]  read_data
);
    reg [3:0] mem [0:15];
    integer i;

    initial begin
        for (i = 0; i < 16; i = i + 1)
            mem[i] = 4'b0000;
    end

    always @(posedge clk) begin
        if (we)
            mem[addr] <= write_data;
    end

    assign read_data = mem[addr];

endmodule

alu_4bit.v
// =====================================================================
// 4-bit ALU
// alu_op directly reuses the instruction opcode[2:0] field for R-type
// instructions (ADD/SUB/AND/OR/XOR/NOT/MOV), see ISA.md for the mapping.
// =====================================================================
module alu_4bit (
    input  wire [3:0] a,        // Rd (current value)
    input  wire [3:0] b,        // Rs (current value)
    input  wire [2:0] alu_op,   // 001 ADD,010 SUB,011 AND,100 OR,101 XOR,110 NOT,111 MOV
    output reg  [3:0] result,
    output wire        zero      // 1 if result == 0
);
    localparam OP_ADD = 3'b001,
               OP_SUB = 3'b010,
               OP_AND = 3'b011,
               OP_OR  = 3'b100,
               OP_XOR = 3'b101,
               OP_NOT = 3'b110,
               OP_MOV = 3'b111;

    always @(*) begin
        case (alu_op)
            OP_ADD: result = a + b;
            OP_SUB: result = a - b;
            OP_AND: result = a & b;
            OP_OR : result = a | b;
            OP_XOR: result = a ^ b;
            OP_NOT: result = ~b;
            OP_MOV: result = b;
            default: result = 4'b0000;
        endcase
    end

    assign zero = (result == 4'b0000);

endmodule

register_file_4bit.v
// =====================================================================
// Register File: 4 general-purpose registers (R0-R3), 4 bits wide.
// Two asynchronous read ports (Rd, Rs), one synchronous write port.
// =====================================================================
module register_file_4bit (
    input  wire        clk,
    input  wire        rst,
    input  wire        we,          // write enable
    input  wire [1:0]  rd_addr,     // destination/write address
    input  wire [1:0]  rs_addr,     // source read address
    input  wire [3:0]  write_data,
    output wire [3:0]  rd_data,     // current value at rd_addr (read before write)
    output wire [3:0]  rs_data      // current value at rs_addr
);
    reg [3:0] regs [0:3];
    integer i;

    always @(posedge clk) begin
        if (rst) begin
            for (i = 0; i < 4; i = i + 1)
                regs[i] <= 4'b0000;
        end else if (we) begin
            regs[rd_addr] <= write_data;
        end
    end

    assign rd_data = regs[rd_addr];
    assign rs_data = regs[rs_addr];

endmodule

cpu_4bit_top.v
// =====================================================================
// 4-bit CPU - Top Level
// Single-cycle, non-pipelined. See ISA.md for the instruction set.
//
// Instruction word (8 bits): [7:4] opcode
//   R-type  (opcode 0001-0111): [3:2] Rd   [1:0] Rs
//   M-type  (opcode 1000-1100): [3:0] addr / immediate   (operates on R0)
//   HALT    (opcode 1111)
// =====================================================================
module cpu_4bit_top (
    input  wire clk,
    input  wire rst,
    output wire [3:0] pc_out,
    output wire [7:0] instr_out,
    output wire [3:0] r0, r1, r2, r3,   // register debug outputs
    output wire        zflag_out,
    output wire        halted
);

    // -----------------------------------------------------------------
    // Program Counter
    // -----------------------------------------------------------------
    reg [3:0] pc;
    assign pc_out = pc;

    // -----------------------------------------------------------------
    // Instruction Memory (ROM) - the demo program (see ISA.md, program.asm)
    // Computes R1 * R2_initial via repeated addition and stores result
    // in data memory address 0.   (3 * 2 = 6)
    // -----------------------------------------------------------------
    reg [7:0] instr_mem [0:15];
    initial begin
        instr_mem[0]  = 8'h83; // LDI 3            -> R0 = 3
        instr_mem[1]  = 8'h74; // MOV R1,R0        -> R1 = 3
        instr_mem[2]  = 8'h82; // LDI 2            -> R0 = 2
        instr_mem[3]  = 8'h78; // MOV R2,R0        -> R2 = 2
        instr_mem[4]  = 8'h81; // LDI 1            -> R0 = 1
        instr_mem[5]  = 8'h7C; // MOV R3,R0        -> R3 = 1
        instr_mem[6]  = 8'h80; // LDI 0            -> R0 = 0 (accumulator reset)
        instr_mem[7]  = 8'h11; // LOOP: ADD R0,R1  -> R0 += R1
        instr_mem[8]  = 8'h2B; //       SUB R2,R3  -> R2 -= 1 (sets Z)
        instr_mem[9]  = 8'hBB; //       JZ 11      -> if Z, goto STORE
        instr_mem[10] = 8'hC7; //       JMP 7      -> else repeat loop
        instr_mem[11] = 8'hA0; // STORE 0          -> MEM[0] = R0
        instr_mem[12] = 8'hF0; // HALT
        instr_mem[13] = 8'h00;
        instr_mem[14] = 8'h00;
        instr_mem[15] = 8'h00;
    end

    wire [7:0] instr = instr_mem[pc];
    assign instr_out = instr;

    // -----------------------------------------------------------------
    // Instruction Decode
    // -----------------------------------------------------------------
    wire [3:0] opcode  = instr[7:4];
    wire [1:0] rd_addr = instr[3:2];
    wire [1:0] rs_addr = instr[1:0];
    wire [3:0] maddr   = instr[3:0];   // address/immediate for M-type & HALT

    wire is_rtype  = (opcode >= 4'b0001) && (opcode <= 4'b0111); // ADD..MOV
    wire is_ldi    = (opcode == 4'b1000);
    wire is_load   = (opcode == 4'b1001);
    wire is_store  = (opcode == 4'b1010);
    wire is_jz     = (opcode == 4'b1011);
    wire is_jmp    = (opcode == 4'b1100);
    wire is_halt   = (opcode == 4'b1111);
    wire is_nop    = (opcode == 4'b0000);

    // -----------------------------------------------------------------
    // Register File
    // -----------------------------------------------------------------
    wire [3:0] rf_rd_data, rf_rs_data;
    reg        rf_we;
    reg  [1:0] rf_waddr;
    reg  [3:0] rf_wdata;

    register_file_4bit RF (
        .clk(clk), .rst(rst), .we(rf_we),
        .rd_addr(is_rtype ? rd_addr : 2'b00),  // M-type/LDI/LOAD always target R0
        .rs_addr(rs_addr),
        .write_data(rf_wdata),
        .rd_data(rf_rd_data),
        .rs_data(rf_rs_data)
    );

    // debug taps - direct register snapshot for waveform/monitor visibility
    assign r0 = RF.regs[0];
    assign r1 = RF.regs[1];
    assign r2 = RF.regs[2];
    assign r3 = RF.regs[3];

    // -----------------------------------------------------------------
    // ALU
    // -----------------------------------------------------------------
    wire [3:0] alu_result;
    wire        alu_zero;

    alu_4bit ALU (
        .a(rf_rd_data),
        .b(rf_rs_data),
        .alu_op(opcode[2:0]),
        .result(alu_result),
        .zero(alu_zero)
    );

    // -----------------------------------------------------------------
    // Zero flag register (latched after R-type ALU ops)
    // -----------------------------------------------------------------
    reg zflag;
    assign zflag_out = zflag;

    // -----------------------------------------------------------------
    // Data Memory
    // -----------------------------------------------------------------
    wire [3:0] mem_read_data;
    reg        mem_we;

    data_memory_4bit DMEM (
        .clk(clk), .we(mem_we),
        .addr(maddr),
        .write_data(rf_rd_data),   // STORE always writes current R0 value
        .read_data(mem_read_data)
    );

    // -----------------------------------------------------------------
    // Halt latch
    // -----------------------------------------------------------------
    reg halt_reg;
    assign halted = halt_reg;

    // -----------------------------------------------------------------
    // Control Unit: combinational control signal generation
    // -----------------------------------------------------------------
    always @(*) begin
        rf_we    = 1'b0;
        rf_wdata = 4'b0000;
        mem_we   = 1'b0;

        if (!halt_reg) begin
            if (is_rtype) begin
                rf_we    = 1'b1;
                rf_wdata = alu_result;
            end else if (is_ldi) begin
                rf_we    = 1'b1;
                rf_wdata = maddr;          // immediate value
            end else if (is_load) begin
                rf_we    = 1'b1;
                rf_wdata = mem_read_data;
            end else if (is_store) begin
                mem_we   = 1'b1;
            end
            // JZ / JMP / HALT / NOP: no register or memory write
        end
    end

    // -----------------------------------------------------------------
    // Sequential: PC update + Z flag update
    // -----------------------------------------------------------------
    always @(posedge clk) begin
        if (rst) begin
            pc       <= 4'b0000;
            zflag    <= 1'b0;
            halt_reg <= 1'b0;
        end else if (halt_reg) begin
            pc <= pc;  // frozen
        end else begin
            // next PC
            if (is_jz && zflag)
                pc <= maddr;
            else if (is_jmp)
                pc <= maddr;
            else
                pc <= pc + 1'b1;

            // zero flag updates only on R-type ALU ops
            if (is_rtype)
                zflag <= alu_zero;

            if (is_halt)
                halt_reg <= 1'b1;
        end
    end

endmodule

tb_cpu_4bit.v
`timescale 1ns/1ps
// =====================================================================
// Testbench: cpu_4bit_top
// Runs the built-in demo program (3 * 2 via repeated addition) and
// prints a full fetch-decode-execute trace each cycle.
// =====================================================================
module tb_cpu_4bit;

    reg clk = 0;
    reg rst;

    wire [3:0] pc;
    wire [7:0] instr;
    wire [3:0] r0, r1, r2, r3;
    wire        zflag;
    wire        halted;

    cpu_4bit_top DUT (
        .clk(clk), .rst(rst),
        .pc_out(pc), .instr_out(instr),
        .r0(r0), .r1(r1), .r2(r2), .r3(r3),
        .zflag_out(zflag), .halted(halted)
    );

    always #5 clk = ~clk;

    // simple mnemonic decoder for trace readability
    function [63:0] mnemonic(input [7:0] i);
        reg [3:0] op;
        begin
            op = i[7:4];
            case (op)
                4'b0000: mnemonic = "NOP     ";
                4'b0001: mnemonic = "ADD     ";
                4'b0010: mnemonic = "SUB     ";
                4'b0011: mnemonic = "AND     ";
                4'b0100: mnemonic = "OR      ";
                4'b0101: mnemonic = "XOR     ";
                4'b0110: mnemonic = "NOT     ";
                4'b0111: mnemonic = "MOV     ";
                4'b1000: mnemonic = "LDI     ";
                4'b1001: mnemonic = "LOAD    ";
                4'b1010: mnemonic = "STORE   ";
                4'b1011: mnemonic = "JZ      ";
                4'b1100: mnemonic = "JMP     ";
                4'b1111: mnemonic = "HALT    ";
                default: mnemonic = "????    ";
            endcase
        end
    endfunction

    initial begin
        $dumpfile("cpu_4bit.vcd");
        $dumpvars(0, tb_cpu_4bit);

        rst = 1;
        repeat (2) @(posedge clk);
        rst = 0;

        $display("PC | INSTR    MNEMONIC | R0 R1 R2 R3 | Z | HALT");
        $display("---+--------------------+-------------+---+-----");

        // run for enough cycles to complete the program, printing each cycle
        repeat (25) begin
            @(posedge clk);
            #1; // let combinational/registered values settle for display
            $display("%2d | %b  %s| %2d %2d %2d %2d |  %b |  %b",
                       pc, instr, mnemonic(instr), r0, r1, r2, r3, zflag, halted);
            if (halted) begin
                $display("\nCPU halted. Final R0=%0d  MEM[0]=%0d", r0, DUT.DMEM.mem[0]);
                $finish;
            end
        end

        $display("\nReached cycle limit without HALT - check program/control logic.");
        $finish;
    end

endmodule

cpu_4bit.vcd
$date
	Sun Jun 28 11:58:02 2026
$end
$version
	Icarus Verilog
$end
$timescale
	1ps
$end
$scope module tb_cpu_4bit $end
$var wire 1 ! zflag $end
$var wire 4 " r3 [3:0] $end
$var wire 4 # r2 [3:0] $end
$var wire 4 $ r1 [3:0] $end
$var wire 4 % r0 [3:0] $end
$var wire 4 & pc [3:0] $end
$var wire 8 ' instr [7:0] $end
$var wire 1 ( halted $end
$var reg 1 ) clk $end
$var reg 1 * rst $end
$scope function mnemonic $end
$var reg 8 + i [7:0] $end
$var reg 4 , op [3:0] $end
$upscope $end
$scope module DUT $end
$var wire 1 ) clk $end
$var wire 1 ( halted $end
$var wire 8 - instr [7:0] $end
$var wire 8 . instr_out [7:0] $end
$var wire 1 / is_rtype $end
$var wire 4 0 pc_out [3:0] $end
$var wire 4 1 r0 [3:0] $end
$var wire 4 2 r1 [3:0] $end
$var wire 4 3 r2 [3:0] $end
$var wire 4 4 r3 [3:0] $end
$var wire 1 * rst $end
$var wire 1 ! zflag_out $end
$var wire 2 5 rs_addr [1:0] $end
$var wire 4 6 rf_rs_data [3:0] $end
$var wire 4 7 rf_rd_data [3:0] $end
$var wire 2 8 rd_addr [1:0] $end
$var wire 4 9 opcode [3:0] $end
$var wire 4 : mem_read_data [3:0] $end
$var wire 4 ; maddr [3:0] $end
$var wire 1 < is_store $end
$var wire 1 = is_nop $end
$var wire 1 > is_load $end
$var wire 1 ? is_ldi $end
$var wire 1 @ is_jz $end
$var wire 1 A is_jmp $end
$var wire 1 B is_halt $end
$var wire 1 C alu_zero $end
$var wire 4 D alu_result [3:0] $end
$var reg 1 E halt_reg $end
$var reg 1 F mem_we $end
$var reg 4 G pc [3:0] $end
$var reg 4 H rf_wdata [3:0] $end
$var reg 1 I rf_we $end
$var reg 1 J zflag $end
$scope module ALU $end
$var wire 3 K alu_op [2:0] $end
$var wire 1 C zero $end
$var wire 4 L b [3:0] $end
$var wire 4 M a [3:0] $end
$var parameter 3 N OP_ADD $end
$var parameter 3 O OP_AND $end
$var parameter 3 P OP_MOV $end
$var parameter 3 Q OP_NOT $end
$var parameter 3 R OP_OR $end
$var parameter 3 S OP_SUB $end
$var parameter 3 T OP_XOR $end
$var reg 4 U result [3:0] $end
$upscope $end
$scope module DMEM $end
$var wire 4 V addr [3:0] $end
$var wire 1 ) clk $end
$var wire 4 W read_data [3:0] $end
$var wire 1 F we $end
$var wire 4 X write_data [3:0] $end
$var integer 32 Y i [31:0] $end
$upscope $end
$scope module RF $end
$var wire 1 ) clk $end
$var wire 2 Z rd_addr [1:0] $end
$var wire 4 [ rd_data [3:0] $end
$var wire 2 \ rs_addr [1:0] $end
$var wire 4 ] rs_data [3:0] $end
$var wire 1 * rst $end
$var wire 1 I we $end
$var wire 4 ^ write_data [3:0] $end
$var integer 32 _ i [31:0] $end
$upscope $end
$upscope $end
$upscope $end
$enddefinitions $end
$comment Show the parameter values. $end
$dumpall
b101 T
b10 S
b100 R
b110 Q
b111 P
b11 O
b1 N
$end
#0
$dumpvars
bx _
bx ^
bx ]
bx \
bx [
bx Z
b10000 Y
bx X
bx W
bx V
bx U
bx M
bx L
bx K
xJ
xI
bx H
bx G
xF
xE
bx D
xC
xB
xA
x@
x?
x>
x=
x<
bx ;
bx :
bx 9
bx 8
bx 7
bx 6
bx 5
bx 4
bx 3
bx 2
bx 1
bx 0
x/
bx .
bx -
bx ,
bx +
1*
0)
x(
bx '
bx &
bx %
bx $
bx #
bx "
x!
$end
#5000
0/
b0 K
b0 7
b0 M
b0 X
b0 [
b0 Z
1C
b0 D
b0 U
0F
b11 H
b11 ^
1I
1?
0>
0<
0@
0A
0B
0=
b1000 9
b0 8
b0 6
b0 L
b0 ]
b11 5
b11 \
b0 :
b0 W
b11 ;
b11 V
b0 "
b0 4
b0 #
b0 3
b0 $
b0 2
b0 %
b0 1
0(
0E
0!
0J
b10000011 '
b10000011 .
b10000011 -
b0 &
b0 0
b0 G
b100 _
1)
#10000
0)
#15000
0*
b100 _
1)
#20000
0)
#25000
b1 Z
0C
b11 D
b11 U
1/
b111 K
b11 H
b11 ^
1I
0?
b111 9
b1 8
b11 6
b11 L
b11 ]
b0 5
b0 \
b100 ;
b100 V
b0 7
b0 M
b0 X
b0 [
b11 %
b11 1
b1110100 '
b1110100 .
b1110100 -
b1 &
b1 0
b1 G
1)
#26000
b111 ,
b1110100 +
#30000
0)
#35000
0/
b0 K
b0 Z
1C
b0 D
b0 U
b10 H
b10 ^
1I
1?
b1000 9
b0 8
b0 6
b0 L
b0 ]
b10 5
b10 \
b10 ;
b10 V
b10000010 '
b10000010 .
b10000010 -
b10 &
b10 0
b10 G
b11 7
b11 M
b11 X
b11 [
b11 $
b11 2
1)
#36000
b1000 ,
b10000010 +
#40000
0)
#45000
b10 Z
0C
b10 D
b10 U
1/
b111 K
b10 H
b10 ^
1I
0?
b111 9
b10 8
b10 6
b10 L
b10 ]
b0 5
b0 \
b1000 ;
b1000 V
b0 7
b0 M
b0 X
b0 [
b10 %
b10 1
b1111000 '
b1111000 .
b1111000 -
b11 &
b11 0
b11 G
1)
#46000
b111 ,
b1111000 +
#50000
0)
#55000
1C
0/
b0 K
b0 Z
b0 D
b0 U
b1 H
b1 ^
1I
1?
b1000 9
b0 8
b11 6
b11 L
b11 ]
b1 5
b1 \
b1 ;
b1 V
b10000001 '
b10000001 .
b10000001 -
b100 &
b100 0
b100 G
b10 7
b10 M
b10 X
b10 [
b10 #
b10 3
1)
#56000
b1000 ,
b10000001 +
#60000
0)
#65000
b11 Z
0C
b1 D
b1 U
1/
b111 K
b1 H
b1 ^
1I
0?
b111 9
b11 8
b1 6
b1 L
b1 ]
b0 5
b0 \
b1100 ;
b1100 V
b0 7
b0 M
b0 X
b0 [
b1 %
b1 1
b1111100 '
b1111100 .
b1111100 -
b101 &
b101 0
b101 G
1)
#66000
b111 ,
b1111100 +
#70000
0)
#75000
1C
b0 D
b0 U
0/
b0 K
b0 Z
b0 H
b0 ^
1I
1?
b1000 9
b0 8
b0 ;
b0 V
b10000000 '
b10000000 .
b10000000 -
b110 &
b110 0
b110 G
b1 7
b1 M
b1 X
b1 [
b1 "
b1 4
1)
#76000
b1000 ,
b10000000 +
#80000
0)
#85000
b11 H
b11 ^
0C
b11 D
b11 U
1/
b1 K
1I
0?
b1 9
b1 5
b1 \
b1 ;
b1 V
b0 7
b0 M
b0 X
b0 [
b11 6
b11 L
b11 ]
b0 %
b0 1
b10001 '
b10001 .
b10001 -
b111 &
b111 0
b111 G
1)
#86000
b1 ,
b10001 +
#90000
0)
#95000
b10 K
b10 Z
b1 H
b1 ^
1I
b10 9
b10 8
b1 6
b1 L
b1 ]
b11 5
b11 \
b1011 ;
b1011 V
b1 D
b1 U
b101011 '
b101011 .
b101011 -
b1000 &
b1000 0
b1000 G
b10 7
b10 M
b10 X
b10 [
b11 %
b11 1
1)
#96000
b10 ,
b101011 +
#100000
0)
#105000
b0 Z
b0 H
b0 ^
0I
0/
b11 K
0C
b1 D
b1 U
1@
b1011 9
b11 7
b11 M
b11 X
b11 [
b1 #
b1 3
b10111011 '
b10111011 .
b10111011 -
b1001 &
b1001 0
b1001 G
1)
#106000
b1011 ,
b10111011 +
#110000
0)
#115000
b11 D
b11 U
b100 K
0@
1A
b1100 9
b1 8
b111 ;
b111 V
b11000111 '
b11000111 .
b11000111 -
b1010 &
b1010 0
b1010 G
1)
#116000
b1100 ,
b11000111 +
#120000
0)
#125000
b110 H
b110 ^
1I
b110 D
b110 U
1/
b1 K
0A
b1 9
b0 8
b11 6
b11 L
b11 ]
b1 5
b1 \
b1 ;
b1 V
b10001 '
b10001 .
b10001 -
b111 &
b111 0
b111 G
1)
#126000
b1 ,
b10001 +
#130000
0)
#135000
1C
b10 K
b10 Z
b0 H
b0 ^
1I
b10 9
b10 8
b1 6
b1 L
b1 ]
b11 5
b11 \
b1011 ;
b1011 V
b0 D
b0 U
b101011 '
b101011 .
b101011 -
b1000 &
b1000 0
b1000 G
b1 7
b1 M
b1 X
b1 [
b110 %
b110 1
1)
#136000
b10 ,
b101011 +
#140000
0)
#145000
b0 Z
0I
0/
b11 K
1C
b0 D
b0 U
1@
b1011 9
b110 7
b110 M
b110 X
b110 [
b0 #
b0 3
1!
1J
b10111011 '
b10111011 .
b10111011 -
b1001 &
b1001 0
b1001 G
1)
#146000
b1011 ,
b10111011 +
#150000
0)
#155000
b10 K
1C
b0 D
b0 U
1F
1<
0@
b1010 9
b0 8
b110 6
b110 L
b110 ]
b0 5
b0 \
b0 ;
b0 V
b10100000 '
b10100000 .
b10100000 -
b1011 &
b1011 0
b1011 G
1)
#156000
b1010 ,
b10100000 +
#160000
0)
#165000
0C
b110 D
b110 U
b111 K
0F
0<
1B
b1111 9
b110 :
b110 W
b11110000 '
b11110000 .
b11110000 -
b1100 &
b1100 0
b1100 G
1)
#166000
b1111 ,
b11110000 +
#170000
0)
#175000
1C
b0 D
b0 U
b0 K
0B
1=
b0 9
1(
1E
b0 '
b0 .
b0 -
b1101 &
b1101 0
b1101 G
1)
#176000
b0 ,
b0 +
